docksible/__init__.py
docksible/arg_validator.py
docksible/cli.py
docksible/constants.py
docksible/docksible.py
docksible/helpers.py
docksible/file_builder/docker_compose_builder.py
docksible/file_builder/docksible_file_builder.py
docksible/file_builder/nginx_conf_builder.py
docksible/file_builder/playbook_builder.py
docksible/templates/app-docker-compose.yml.j2
docksible/templates/base-docker-compose.yml.j2
docksible/templates/base-nginx.conf.j2
docksible/templates/base-playbook.yml
docksible/templates/db-docker-compose.yml.j2
docksible/templates/letsencrypt-docker-compose.yml.j2
docksible/templates/letsencrypt-tasks.yml
docksible/templates/nginx-ssl.conf.j2
docksible/templates/phpmyadmin-service.yml.j2
docksible/templates/playbook-run-tasks.yml
docksible/templates/ssh-proxy-service.yml.j2
docksible/templates/wp-cli-service.yml.j2
docksible-1.0.1.dist-info/licenses/LICENSE.txt
docksible-1.0.1.dist-info/METADATA
docksible-1.0.1.dist-info/WHEEL
docksible-1.0.1.dist-info/entry_points.txt
docksible-1.0.1.dist-info/top_level.txt
docksible-1.0.1.dist-info/RECORD
