Metadata-Version: 2.4
Name: docksible
Version: 1.0.1
Summary: Deploy and set up Docker Compose based web apps with Ansible
Author-email: Belal Ibrahim <belal.ibrahim@proton.me>
Project-URL: Homepage, https://github.com/belal-i/docksible
Project-URL: Issues, https://github.com/belal-i/docksible/issues
Classifier: Development Status :: 4 - Beta
Classifier: Environment :: Console
Classifier: Framework :: Ansible
Classifier: Programming Language :: Python :: 3
Classifier: Intended Audience :: Developers
Classifier: Intended Audience :: Information Technology
Classifier: Intended Audience :: System Administrators
Classifier: License :: OSI Approved :: Apache Software License
Requires-Python: >=3.9
License-File: LICENSE.txt
Requires-Dist: ansible-core<2.24,>=2.15
Requires-Dist: ansible-runner>=2.4
Requires-Dist: crossplane
Dynamic: license-file
